orpheuspypractice/__init__.py
orpheuspypractice/dependency_action.py
orpheuspypractice/dependency_manager.py
orpheuspypractice/dummy_use_python_ci.py
orpheuspypractice/link2abc_cli.py
orpheuspypractice/link2abc_integration.py
orpheuspypractice/oiv.py
orpheuspypractice/olca.py
orpheuspypractice-0.3.1.dist-info/licenses/LICENSE
orpheuspypractice-0.3.1.dist-info/METADATA
orpheuspypractice-0.3.1.dist-info/WHEEL
orpheuspypractice-0.3.1.dist-info/entry_points.txt
orpheuspypractice-0.3.1.dist-info/top_level.txt
orpheuspypractice-0.3.1.dist-info/RECORD
