Metadata-Version: 2.4
Name: orpheuspypractice
Version: 0.3.1
Summary: AI-Powered Music Generation & Interactive Composition Toolkit
Home-page: https://github.com/jgwill/orpheuspypractice
Author: JGWill
Author-email: jgi@jgwill.com
Classifier: Programming Language :: Python :: 3
Classifier: License :: OSI Approved :: MIT License
Classifier: Operating System :: OS Independent
Requires-Python: >=3.6
License-File: LICENSE
Requires-Dist: tlid
Requires-Dist: requests
Requires-Dist: music21
Requires-Dist: ipython
Requires-Dist: jgcmlib>=1.0.59
Requires-Dist: jghfmanager>=0.1.5
Requires-Dist: langchain
Requires-Dist: langchain_openai
Requires-Dist: langchain_community
Requires-Dist: arxiv
Requires-Dist: pyyaml
Requires-Dist: python-dotenv
Requires-Dist: langgraph
Requires-Dist: wikipedia
Requires-Dist: llm
Requires-Dist: pandas
Requires-Dist: numpy
Requires-Dist: langchain-experimental
Requires-Dist: langsmith
Requires-Dist: numexpr
Requires-Dist: strip-tags
Requires-Dist: jaraco.functools
Requires-Dist: jaraco.context
Dynamic: author
Dynamic: author-email
Dynamic: classifier
Dynamic: description
Dynamic: description-content-type
Dynamic: home-page
Dynamic: license-file
Dynamic: requires-dist
Dynamic: requires-python
Dynamic: summary
